cancer_prediction/__init__.py
cancer_prediction/app.py
cancer_prediction/cancer_model.py
cancer_prediction/streamlit_app.py
packaging_publishing-0.1.0.dist-info/LICENSE
packaging_publishing-0.1.0.dist-info/METADATA
packaging_publishing-0.1.0.dist-info/WHEEL
packaging_publishing-0.1.0.dist-info/RECORD
