Metadata-Version: 2.3
Name: packaging-publishing
Version: 0.1.0
Summary: 
Author: Zi-Hao Huang
Author-email: 134923928+BioJoe-Hzh@users.noreply.github.com
Requires-Python: >=3.12
Classifier: Programming Language :: Python :: 3
Classifier: Programming Language :: Python :: 3.12
Classifier: Programming Language :: Python :: 3.13
Requires-Dist: matplotlib (>=3.10.1,<4.0.0)
Requires-Dist: numpy (>=2.2.5,<3.0.0)
Requires-Dist: pandas (>=2.2.3,<3.0.0)
Requires-Dist: streamlit (>=1.45.0,<2.0.0)
Requires-Dist: typer (>=0.15.3,<0.16.0)
